README.rst
setup.py
sample_tests/__init__.py
sample_tests/math_test.py
unitdox/__init__.py
unitdox/__main__.py
unitdox.egg-info/PKG-INFO
unitdox.egg-info/SOURCES.txt
unitdox.egg-info/dependency_links.txt
unitdox.egg-info/entry_points.txt
unitdox.egg-info/pbr.json
unitdox.egg-info/top_level.txt