Metadata-Version: 1.1
Name: unitdox
Version: 0.1
Summary: UNKNOWN
Home-page: https://github.com/FabienArcellier/unitdox
Author: Fabien Arcellier
Author-email: fabien.arcellier@gmail.com
License: License :: OSI Approved :: BSD License
Platform: UNKNOWN
Classifier: Programming Language :: Python
Classifier: Development Status :: 1 - Planning
Classifier: License :: OSI Approved :: BSD License
Classifier: Operating System :: OS Independent
Classifier: Programming Language :: Python :: 2.7
Classifier: Programming Language :: Python :: 3.4
Classifier: Programming Language :: Python :: 3.5
Classifier: Topic :: Software Development :: Testing
Classifier: Topic :: Software Development :: Documentation
